LICENSE.txt
MANIFEST.in
README.md
requirements.txt
setup.py
iam_docker_run/__init__.py
iam_docker_run/__main__.py
iam_docker_run/aws_iam_utils.py
iam_docker_run/aws_util_exceptions.py
iam_docker_run/docker_cli_utils.py
iam_docker_run/iam_docker_run.py
iam_docker_run/shell_utils.py
iam_docker_run/version.py
iam_docker_run.egg-info/PKG-INFO
iam_docker_run.egg-info/SOURCES.txt
iam_docker_run.egg-info/dependency_links.txt
iam_docker_run.egg-info/entry_points.txt
iam_docker_run.egg-info/requires.txt
iam_docker_run.egg-info/top_level.txt