Metadata-Version: 2.1
Name: iam-docker-run
Version: 0.3.8
Summary: Run Docker containers within the context of an AWS IAM Role, and other development workflow helpers.
Home-page: https://github.com/billtrust/iam-docker-run
Author: Doug Kerwin
Author-email: dwkerwin@gmail.com
License: MIT
Keywords: aws,iam,iam-role,docker
Platform: UNKNOWN
Classifier: Intended Audience :: Developers
Classifier: Natural Language :: English
Classifier: License :: OSI Approved :: MIT License
Classifier: Programming Language :: Python
Classifier: Programming Language :: Python :: 2.7
Classifier: Programming Language :: Python :: 3
Classifier: Programming Language :: Python :: 3.6
License-File: LICENSE.txt
